ABayesianC/__init__.py
ABayesianC/tools.py
ABayesianC-1.0.8.dist-info/LICENSE
ABayesianC-1.0.8.dist-info/METADATA
ABayesianC-1.0.8.dist-info/WHEEL
ABayesianC-1.0.8.dist-info/top_level.txt
ABayesianC-1.0.8.dist-info/RECORD
