Metadata-Version: 2.1
Name: ABayesianC
Version: 1.0.8
Summary: A general-purpose approximate Bayesian calculation
Home-page: https://github.com/janursa/ABayesianC
Author: Jalil Nourisa
Author-email: jalil.nourisa@gmail.com
License: UNKNOWN
Platform: UNKNOWN
Classifier: Programming Language :: Python :: 3
Classifier: License :: OSI Approved :: MIT License
Classifier: Operating System :: OS Independent
Requires-Python: >=3.6
Requires-Dist: diversipy (>=0.8)
Requires-Dist: plotly (>=4.6.0)
Requires-Dist: pandas (>=1.0.3)
Requires-Dist: numpy (>=1.18.4)
Requires-Dist: psutil (>=5.7.0)
Requires-Dist: pprogress (>=0.0.5)
Requires-Dist: mpi4py (>=3.0.3)
Requires-Dist: requests (>=2.23.0)
